active_users/__init__.py
active_users/keys.py
active_users/middleware.py
active_users/settings.py
active_users/api/__init__.py
active_users/api/urls.py
active_users/api/views.py
django_active_users-0.4.1.dist-info/LICENSE
django_active_users-0.4.1.dist-info/METADATA
django_active_users-0.4.1.dist-info/WHEEL
django_active_users-0.4.1.dist-info/top_level.txt
django_active_users-0.4.1.dist-info/RECORD
