Metadata-Version: 2.1
Name: django-active-users
Version: 0.4.1
Summary: Monitoring of active users in Django using Redis
Home-page: https://github.com/n-elloco/django-active-users
Author: Nikita Ekaterinchuk
Author-email: en.elloco@gmail.com
License: MIT
Platform: UNKNOWN
Classifier: Development Status :: 5 - Production/Stable
Classifier: Environment :: Web Environment
Classifier: Intended Audience :: Developers
Classifier: License :: OSI Approved :: MIT License
Classifier: Operating System :: OS Independent
Classifier: Programming Language :: Python
Classifier: Programming Language :: Python :: 3.6
Classifier: Programming Language :: Python :: 3.7
Classifier: Programming Language :: Python :: 3.8
Classifier: Programming Language :: Python :: 3.9
Classifier: Programming Language :: Python :: 3.10
Classifier: Programming Language :: Python :: 3.11
Requires-Dist: django >=1.11
Requires-Dist: django-redis >=4.9.0
Requires-Dist: six
